iotics/__init__.py
iotics/lib/__init__.py
iotics/lib/identity/__init__.py
iotics/lib/identity/const.py
iotics/lib/identity/error.py
iotics/lib/identity/api/__init__.py
iotics/lib/identity/api/advanced_api.py
iotics/lib/identity/api/advanced_api_keys.py
iotics/lib/identity/api/advanced_api_proof.py
iotics/lib/identity/api/high_level_api.py
iotics/lib/identity/api/regular_api.py
iotics/lib/identity/crypto/__init__.py
iotics/lib/identity/crypto/identity.py
iotics/lib/identity/crypto/issuer.py
iotics/lib/identity/crypto/jwt.py
iotics/lib/identity/crypto/key_pair_secrets.py
iotics/lib/identity/crypto/keys.py
iotics/lib/identity/crypto/proof.py
iotics/lib/identity/register/__init__.py
iotics/lib/identity/register/document.py
iotics/lib/identity/register/document_builder.py
iotics/lib/identity/register/document_helper.py
iotics/lib/identity/register/key_pair.py
iotics/lib/identity/register/keys.py
iotics/lib/identity/register/resolver.py
iotics/lib/identity/register/rest_resolver.py
iotics/lib/identity/validation/__init__.py
iotics/lib/identity/validation/authentication.py
iotics/lib/identity/validation/document.py
iotics/lib/identity/validation/identity.py
iotics/lib/identity/validation/proof.py
iotics_identity-2.1.2.dist-info/LICENSE
iotics_identity-2.1.2.dist-info/METADATA
iotics_identity-2.1.2.dist-info/WHEEL
iotics_identity-2.1.2.dist-info/entry_points.txt
iotics_identity-2.1.2.dist-info/top_level.txt
iotics_identity-2.1.2.dist-info/zip-safe
iotics_identity-2.1.2.dist-info/RECORD
