Metadata-Version: 2.1
Name: iotics-identity
Version: 2.1.2
Summary: Iotics DID specification Python library
Home-page: https://github.com/Iotic-Labs/iotics-identity-py
Author: Iotics
Author-email: info@iotics.com
License: UNKNOWN
Project-URL: Bug Tracker, https://github.com/Iotic-Labs/iotics-identity-py/issues
Project-URL: Changelog, https://github.com/Iotic-Labs/iotics-identity-py/releases
Keywords: iotics,did,decentralised identity,decentralized identity,digital twin
Platform: any
Classifier: Intended Audience :: Developers
Classifier: License :: OSI Approved :: Apache Software License
Classifier: Operating System :: OS Independent
Classifier: Programming Language :: Python
Classifier: Programming Language :: Python :: 3.8
Classifier: Programming Language :: Python :: 3.9
Classifier: Programming Language :: Python :: 3.10
Classifier: Programming Language :: Python :: 3.11
Classifier: Programming Language :: Python :: 3.12
Classifier: Topic :: Software Development :: Libraries :: Python Modules
Requires-Dist: requests (>=2.32.0)
Requires-Dist: base58 (==2.1.1)
Requires-Dist: PyJWT (==2.7.0)
Requires-Dist: mnemonic (==0.20)
Requires-Dist: cryptography (<44,>=43.0.1)
Provides-Extra: dev
Requires-Dist: tox (==4.6.4) ; extra == 'dev'
Provides-Extra: lint
Requires-Dist: flake8 (==6.0.0) ; extra == 'lint'
Requires-Dist: pylint (==2.17.4) ; extra == 'lint'
Requires-Dist: pylint-quotes (==0.2.3) ; extra == 'lint'
Requires-Dist: mypy (==1.4.1) ; extra == 'lint'
Requires-Dist: types-requests ; extra == 'lint'
Provides-Extra: test
Requires-Dist: pytest (==7.4.0) ; extra == 'test'
Requires-Dist: pytest-bdd (==6.1.1) ; extra == 'test'
Requires-Dist: pytest-cov (==4.1.0) ; extra == 'test'
Requires-Dist: pytest-html (==3.2.0) ; extra == 'test'
Requires-Dist: requests-mock (==1.11.0) ; extra == 'test'
